{
  "name": "Kablo Yapımı",
  "category": "modern_industrialization:electric_age",
  "icon": "modern_industrialization:tin_wire",
  "pages": [
    {
      "type": "text",
      "text": "Kok Tozunu bir karıştırıcıda Su ile karıştırın ve Sentetik Yağ elde etmek için Buharlı Maden Eritme Ocağında yakabileceğiniz Ham Sentetik Yağ elde edersiniz. Kâğıt ile karıştırdığınızda kauçuk levhalar elde edersiniz!$(br2)Bu sürecin otomatikleştirilmesi şiddetle tavsiye edilir! Kâğıdın kâğıt hamuru kullanılarak ahşaptan yapılabileceğini unutmayın."
    },
    {
      "type": "crafting",
      "recipe": "modern_industrialization:steam_age/steel/wiremill_asbl",
      "text": "Teller için Tel Değirmenine ihtiyacınız olacak! Kabloları elde etmek için bu telleri kauçuk levhalarla birleştirin!"
    }
  ],
  "sortnum": 100
}